{
  "collectionName": "components_core_footers",
  "info": {
    "displayName": "Footer",
    "icon": "bold",
    "description": ""
  },
  "options": {},
  "attributes": {
    "title": {
      "type": "string"
    },
    "logoUrl": {
      "type": "string"
    },
    "description": {
      "type": "text"
    },
    "newsletterTitle": {
      "type": "string"
    },
    "copyright": {
      "type": "string"
    },
    "socialLinks": {
      "type": "component",
      "repeatable": true,
      "component": "core.social-link"
    },
    "bottomLinks": {
      "type": "component",
      "repeatable": true,
      "component": "core.link"
    },
    "columns": {
      "type": "component",
      "repeatable": true,
      "component": "core.footer-column"
    }
  }
}
